agentcrypt/__init__.py
agentcrypt/crypto.py
agentcrypt/exceptions.py
agentcrypt/io.py
agentcrypt/py2compat.py
agentcrypt-0.5.dist-info/DESCRIPTION.rst
agentcrypt-0.5.dist-info/METADATA
agentcrypt-0.5.dist-info/RECORD
agentcrypt-0.5.dist-info/WHEEL
agentcrypt-0.5.dist-info/metadata.json
agentcrypt-0.5.dist-info/top_level.txt
agentcrypt-0.5.dist-info/zip-safe
