Metadata-Version: 2.0
Name: agentcrypt
Version: 0.5
Summary: Symmetric encryption using the ssh-agent
Home-page: https://github.com/dheuvels/agentcrypt
Author: Dirk Heuvels
Author-email: coding@heuvels.de
License: GNU General Public License v3
Download-URL: https://github.com/dheuvels/agentcrypt/archive/v0.5.tar.gz
Keywords: agentcrypt
Platform: UNKNOWN
Classifier: Development Status :: 4 - Beta
Classifier: Intended Audience :: Developers
Classifier: License :: OSI Approved :: GNU General Public License v3 (GPLv3)
Classifier: Natural Language :: English
Classifier: Programming Language :: Python :: 2
Classifier: Programming Language :: Python :: 2.7
Classifier: Programming Language :: Python :: 3
Classifier: Programming Language :: Python :: 3.4
Classifier: Programming Language :: Python :: 3.5
Classifier: Programming Language :: Python :: 3.6
Classifier: Programming Language :: Python :: 3.7
Requires-Dist: PyYAML
Requires-Dist: cryptography
Requires-Dist: future
Requires-Dist: future
Requires-Dist: paramiko
